MANIFEST.in
README.md
setup.cfg
setup.py
mattapi/__init__.py
mattapi.egg-info/PKG-INFO
mattapi.egg-info/SOURCES.txt
mattapi.egg-info/dependency_links.txt
mattapi.egg-info/entry_points.txt
mattapi.egg-info/not-zip-safe
mattapi.egg-info/requires.txt
mattapi.egg-info/top_level.txt
mattapi/api/__init__.py
mattapi/api/enums.py
mattapi/api/errors.py
mattapi/api/location.py
mattapi/api/os_helpers.py
mattapi/api/rectangle.py
mattapi/api/settings.py
mattapi/api/finder/__init__.py
mattapi/api/finder/finder.py
mattapi/api/finder/image_search.py
mattapi/api/finder/pattern.py
mattapi/api/finder/text_search.py
mattapi/api/highlight/__init__.py
mattapi/api/highlight/highlight_circle.py
mattapi/api/highlight/highlight_rectangle.py
mattapi/api/highlight/screen_highlight.py
mattapi/api/keyboard/__init__.py
mattapi/api/keyboard/key.py
mattapi/api/keyboard/keyboard.py
mattapi/api/keyboard/keyboard_api.py
mattapi/api/keyboard/keyboard_util.py
mattapi/api/mouse/__init__.py
mattapi/api/mouse/mouse.py
mattapi/api/mouse/mouse_controller.py
mattapi/api/mouse/xmouse.py
mattapi/api/save_debug_image/__init__.py
mattapi/api/save_debug_image/save_image.py
mattapi/api/screen/__init__.py
mattapi/api/screen/display.py
mattapi/api/screen/region.py
mattapi/api/screen/region_utils.py
mattapi/api/screen/screen.py
mattapi/api/screen/screenshot_image.py
mattapi/base/__init__.py
mattapi/base/target.py
mattapi/base/testcase.py
mattapi/configuration/__init__.py
mattapi/configuration/config_parser.py
mattapi/control_center/__init__.py
mattapi/control_center/commands.py
mattapi/control_center/assets/.DS_Store
mattapi/control_center/assets/asset-manifest.json
mattapi/control_center/assets/favicon.ico
mattapi/control_center/assets/index.html
mattapi/control_center/assets/manifest.json
mattapi/control_center/assets/service-worker.js
mattapi/control_center/assets/images/firefox.png
mattapi/control_center/assets/images/notepad.png
mattapi/control_center/assets/static/.DS_Store
mattapi/control_center/assets/static/css/2.3c6b4139.chunk.css
mattapi/control_center/assets/static/css/2.3c6b4139.chunk.css.map
mattapi/control_center/assets/static/css/main.c73dc7db.chunk.css
